assimp/__init__.py
assimp/core.py
assimp/errors.py
assimp/formats.py
assimp/helper.py
assimp/material.py
assimp/postprocess.py
assimp/structs.py
assimp-4.1.4.dist-info/METADATA
assimp-4.1.4.dist-info/RECORD
assimp-4.1.4.dist-info/WHEEL
assimp-4.1.4.dist-info/top_level.txt
